{
  "id": "Abhi Mujh Mein",
  "songName": "Abhi Mujh Mein",
  "artist": "Sonu Nigam",
  "key": "G",
  "chords": ["G"],
  "customTags": ["Soft", "Thehraav"],
  "lyrics": {
    "hindi": "",
    "english": "Abhi mujh mein kahin\nBaaqi thodi si hai zindagi\nJagi dhadkan nayi\nJaana zinda hoon main toh abhi\nKuch aisi lagan is lamhe mein hai\nYe lamha kahan tha mera\nAb hai saamne, ise chhoo loon zara?\nMar jaaun ya jee loon zara?\nKhushiyan choom loon ya ro loon zara?\nMar jaaun ya jee loon zara?\nHo, abhi mujh mein kahin\nBaaqi thodi si hai zindagi\nHo, dhoop mein jalte hue tan ko\nChhaaya ped ki mil gayi\nRoothe bachche ki hasi jaise\nPhuslaane se phir khil gayi\nKuch aisa hi\nAb mehsoos dil ko ho raha hai\nBarson ke purane\nZakhm pe marham laga sa hai\nKuch aisa rehem is lamhe mein hai\nYe lamha kahan tha mera\nAb hai saamne, ise chhoo loon zara?\nMar jaaun ya jee loon zara?\nKhushiyan choom loon ya ro loon zara?\nMar jaaun ya jee loon zara?\nDor se tooti patang jaisi\nThi ye zindgaani meri\nAaj ho, kal ho mera na ho\nHar din thi kahaani meri\nEk bandhan naya\nPeechhe se ab mujhko bulaaye\nAane waale kal ki\nKyun fikar mujhko sata jaaye\nEk aisi chubhan is lamhe mein hai\nYe lamha kahan tha mera\nAb hai saamne ise chhoo loon zara?\nMar jaaun ya jee loon zara?\nKhushiyan choom loon ya ro loon zara?\nMar jaaun ya jee loon zara?"
  }
}